README.rst
setup.py
peval/__init__.py
peval/highlevelapi.py
peval/tags.py
peval/wisdom.py
peval.egg-info/PKG-INFO
peval.egg-info/SOURCES.txt
peval.egg-info/dependency_links.txt
peval.egg-info/requires.txt
peval.egg-info/top_level.txt
peval/components/__init__.py
peval/components/fold.py
peval/components/inline.py
peval/components/prune_assignments.py
peval/components/prune_cfg.py
peval/core/__init__.py
peval/core/callable.py
peval/core/cfg.py
peval/core/expression.py
peval/core/function.py
peval/core/gensym.py
peval/core/mangler.py
peval/core/reify.py
peval/core/scope.py
peval/tools/__init__.py
peval/tools/dispatcher.py
peval/tools/immutable.py
peval/tools/utils.py
peval/tools/walker.py
tests/__init__.py
tests/test_highlevelapi.py
tests/test_tags.py
tests/utils.py
tests/test_components/__init__.py
tests/test_components/test_fold.py
tests/test_components/test_inline.py
tests/test_components/test_prune_cfg.py
tests/test_core/__init__.py
tests/test_core/test_callable.py
tests/test_core/test_cfg.py
tests/test_core/test_expression.py
tests/test_core/test_function.py
tests/test_core/test_mangler.py
tests/test_core/test_reify.py
tests/test_tools/__init__.py
tests/test_tools/test_immutable.py
tests/test_tools/test_utils.py
tests/test_tools/test_walker.py