Metadata-Version: 1.1
Name: peval
Version: 0.1.0
Summary: Partial evaluation on AST level
Home-page: https://github.com/fjarri/peval
Author: Bogdan Opanchuk
Author-email: bogdan@opanchuk.net
License: UNKNOWN
Keywords: AST partial optimization
Platform: any
Classifier: Development Status :: 3 - Alpha
Classifier: Operating System :: OS Independent
Classifier: Intended Audience :: Science/Research
Classifier: Intended Audience :: Developers
Classifier: License :: OSI Approved :: MIT License
Classifier: Programming Language :: Python
Classifier: Programming Language :: Python :: 3
Classifier: Programming Language :: Python :: 3.5
Classifier: Topic :: Software Development :: Libraries :: Python Modules
Classifier: Topic :: Software Development :: Code Generators
